README.md
setup.py
version_information/__init__.py
version_information/version.py
version_information/version_information.py
version_information.egg-info/PKG-INFO
version_information.egg-info/SOURCES.txt
version_information.egg-info/dependency_links.txt
version_information.egg-info/top_level.txt