Metadata-Version: 1.0
Name: version_information
Version: 1.0.4
Summary: Version information:
Home-page: https://github.com/jrjohansson/version_information
Author: J. Robert Johansson
Author-email: jrjohansson@gmail.com
License: BSD
Platform: Linux
Platform: Mac OSX
Platform: Unix
Platform: Windows
